okn_py_updater/__init__.py
okn_py_updater/okn_py_updater.py
okn_py_updater-3.0.2.dist-info/LICENSE
okn_py_updater-3.0.2.dist-info/METADATA
okn_py_updater-3.0.2.dist-info/WHEEL
okn_py_updater-3.0.2.dist-info/top_level.txt
okn_py_updater-3.0.2.dist-info/RECORD
