Metadata-Version: 2.1
Name: okn_py_updater
Version: 3.0.2
Summary: Python Library for OKN Data Updater
Author-email: Zaw Lin Tun <zawlintun1511@gmail.com>
Project-URL: Homepage, https://github.com/ZawLinTun16925410/okn_data_updater
Project-URL: Bug Tracker, https://github.com/ZawLinTun16925410/okn_data_updater/issues
Classifier: Programming Language :: Python :: 3
Classifier: License :: OSI Approved :: Apache Software License
Classifier: Operating System :: OS Independent
Requires-Python: >=3.6
License-File: LICENSE
